py18n/__init__.py
py18n/extension.py
py18n/i18n.py
py18n/language.py
Py18n-1.1.1.dist-info/LICENSE
Py18n-1.1.1.dist-info/METADATA
Py18n-1.1.1.dist-info/WHEEL
Py18n-1.1.1.dist-info/top_level.txt
Py18n-1.1.1.dist-info/RECORD
