Metadata-Version: 2.1
Name: Py18n
Version: 1.1.1
Summary: I18n for Discord.py
Home-page: https://github.com/starsflower/py18n
Author: starsflower
License: UNKNOWN
Platform: UNKNOWN
Requires-Dist: discord.py
